pig_frame/__init__.py
pig_frame/asserts.py
pig_frame/common.py
pig_frame/db.py
pig_frame/ddt.py
pig_frame/decorators.py
pig_frame/exceptions.py
pig_frame/http_request.py
pig_frame/mail.py
pig_frame/my_thread.py
pig_frame/num_util.py
pig_frame/runner.py
pig_frame/se_common.py
pig_frame/task_job.py
pig_frame/task_scheduler.py
pig_frame/template.py
pig_frame/test_case.py
pig_frame/test_suite.py
pig_frame/utils.py
pig_frame/xmind_util.py
pig_frame/log/__init__.py
pig_frame/log/config.py
pig_frame/log/handlers.py
pig_frame/skeleton/README.md
pig_frame/skeleton/requirements.txt
pig_frame/skeleton/conf/global.json
pig_frame/skeleton/conf/pro.json
pig_frame/skeleton/conf/readme.md
pig_frame/skeleton/conf/scheduler.json
pig_frame/skeleton/conf/test.json
pig_frame/skeleton/conf/uat.json
pig_frame/skeleton/conf/bbbb/demo2.json
pig_frame/skeleton/testcases/assert_demo.py
pig_frame/skeleton/testcases/demo1.py
pig_frame/skeleton/testcases/html_demo.py
pig_frame/skeleton/testcases/idl_demo.py
pig_frame/skeleton/testcases/readme.md
pig_frame/skeleton/testcases/run_test_suite.py
pig_frame/skeleton/testcases/测试场景/idl_demo.py
pig_frame/skeleton/testcases/测试场景/readme.md
pig_frame/skeleton/testcases/测试物料/demo1.py
pig_frame/skeleton/testcases/测试物料/readme.md
pig_frame/templates/idl.json
pig_frame/templates/test_case_report.html
pig_frame/templates/test_suite_report.html
pig_sdk-1.3.1.dist-info/METADATA
pig_sdk-1.3.1.dist-info/WHEEL
pig_sdk-1.3.1.dist-info/top_level.txt
pig_sdk-1.3.1.dist-info/RECORD
