Metadata-Version: 2.1
Name: pig-sdk
Version: 1.3.1
Summary: 接口自动化框架
Home-page: https://git.oak.net.cn/test_group/pigs_sdk/-/tree/master/pig_frame
Author: chengwenping2
Author-email: chengwenping2@newhope.cn
Maintainer: chengwenping2
Maintainer-email: chengwenping2@newhope.cn
License: MIT
Keywords: 自动化
Classifier: Development Status :: 4 - Beta
Classifier: License :: OSI Approved :: MIT License
Classifier: Operating System :: OS Independent
Classifier: Programming Language :: Python :: 3
Classifier: Programming Language :: Python :: 3.9
Classifier: Topic :: Utilities
Requires-Python: >=3.9
Requires-Dist: jsonpath (~=0.82)
Requires-Dist: PyMySQL (~=1.0.3)
Requires-Dist: jmespath (~=0.10.0)
Requires-Dist: Requests (~=2.31.0)
Requires-Dist: setuptools (~=56.0.0)
Requires-Dist: psutil (~=5.9.5)
Requires-Dist: XMind (~=1.2.0)
Requires-Dist: APScheduler (~=3.10.1)
Requires-Dist: pyjson5 (~=1.6.2)
Requires-Dist: json5 (~=0.9.14)
Requires-Dist: Faker (~=18.10.1)
Requires-Dist: Jinja2 (~=3.1.2)
Requires-Dist: termcolor (~=2.3.0)
Requires-Dist: openpyxl (~=3.1.2)
Requires-Dist: urllib3 (~=1.26.16)
Requires-Dist: beautifulsoup4 (~=4.12.2)
Requires-Dist: sshtunnel (~=0.4.0)
Requires-Dist: redis (~=5.0.0)
Provides-Extra: gui
Requires-Dist: PyQt6 (~=6.2.0) ; extra == 'gui'
